README.rst
setup.py
slacker/__init__.py
slacker/utils.py
slacker_ae.egg-info/PKG-INFO
slacker_ae.egg-info/SOURCES.txt
slacker_ae.egg-info/dependency_links.txt
slacker_ae.egg-info/top_level.txt