Metadata-Version: 1.1
Name: slacker-ae
Version: 0.9.44
Summary: Slack API client (App Engine)
Home-page: http://github.com/baole/slacker/
Author: Bao Le
Author-email: leducbao@gmail.com
License: http://www.apache.org/licenses/LICENSE-2.0
Keywords: slack api
Platform: UNKNOWN
Classifier: Intended Audience :: Developers
Classifier: License :: OSI Approved :: Apache Software License
Classifier: Natural Language :: English
Classifier: Programming Language :: Python
Classifier: Programming Language :: Python :: 2.6
Classifier: Programming Language :: Python :: 2.7
Classifier: Programming Language :: Python :: 3
Classifier: Programming Language :: Python :: 3.3
Classifier: Programming Language :: Python :: 3.4
